{
  "swagger": "2.0",
  "info": {
    "title": "sirosimes/mikura/v1/pipeline.proto",
    "version": "version not set"
  },
  "tags": [
    {
      "name": "PipelineService"
    }
  ],
  "consumes": [
    "application/json"
  ],
  "produces": [
    "application/json"
  ],
  "paths": {
    "/v1/pipeline-runs/{runId}": {
      "get": {
        "operationId": "PipelineService_GetPipelineStatus",
        "responses": {
          "200": {
            "description": "A successful response.",
            "schema": {
              "$ref": "#/definitions/v1GetPipelineStatusResponse"
            }
          },
          "default": {
            "description": "An unexpected error response.",
            "schema": {
              "$ref": "#/definitions/rpcStatus"
            }
          }
        },
        "parameters": [
          {
            "name": "runId",
            "in": "path",
            "required": true,
            "type": "string"
          }
        ],
        "tags": [
          "PipelineService"
        ]
      }
    },
    "/v1/pipelines": {
      "get": {
        "operationId": "PipelineService_ListPipelines",
        "responses": {
          "200": {
            "description": "A successful response.",
            "schema": {
              "$ref": "#/definitions/sirosimesmikurav1ListPipelinesResponse"
            }
          },
          "default": {
            "description": "An unexpected error response.",
            "schema": {
              "$ref": "#/definitions/rpcStatus"
            }
          }
        },
        "parameters": [
          {
            "name": "pagination.page",
            "description": "Page number (1-indexed).",
            "in": "query",
            "required": false,
            "type": "integer",
            "format": "int32"
          },
          {
            "name": "pagination.pageSize",
            "description": "Number of items per page (max enforced per-service).",
            "in": "query",
            "required": false,
            "type": "integer",
            "format": "int32"
          },
          {
            "name": "pagination.sortBy",
            "description": "Field name to sort by.",
            "in": "query",
            "required": false,
            "type": "string"
          },
          {
            "name": "pagination.sortOrder",
            "description": "Sort direction.",
            "in": "query",
            "required": false,
            "type": "string",
            "enum": [
              "SORT_ORDER_UNSPECIFIED",
              "SORT_ORDER_ASC",
              "SORT_ORDER_DESC"
            ],
            "default": "SORT_ORDER_UNSPECIFIED"
          },
          {
            "name": "activeOnly",
            "in": "query",
            "required": false,
            "type": "boolean"
          }
        ],
        "tags": [
          "PipelineService"
        ]
      },
      "post": {
        "operationId": "PipelineService_CreatePipeline",
        "responses": {
          "200": {
            "description": "A successful response.",
            "schema": {
              "$ref": "#/definitions/sirosimesmikurav1CreatePipelineResponse"
            }
          },
          "default": {
            "description": "An unexpected error response.",
            "schema": {
              "$ref": "#/definitions/rpcStatus"
            }
          }
        },
        "parameters": [
          {
            "name": "body",
            "description": "CreatePipelineRequest is the request for creating a pipeline definition.",
            "in": "body",
            "required": true,
            "schema": {
              "$ref": "#/definitions/sirosimesmikurav1CreatePipelineRequest"
            }
          }
        ],
        "tags": [
          "PipelineService"
        ]
      }
    },
    "/v1/pipelines/{pipelineId}/run": {
      "post": {
        "operationId": "PipelineService_RunPipeline",
        "responses": {
          "200": {
            "description": "A successful response.",
            "schema": {
              "$ref": "#/definitions/v1RunPipelineResponse"
            }
          },
          "default": {
            "description": "An unexpected error response.",
            "schema": {
              "$ref": "#/definitions/rpcStatus"
            }
          }
        },
        "parameters": [
          {
            "name": "pipelineId",
            "in": "path",
            "required": true,
            "type": "string"
          },
          {
            "name": "body",
            "in": "body",
            "required": true,
            "schema": {
              "$ref": "#/definitions/PipelineServiceRunPipelineBody"
            }
          }
        ],
        "tags": [
          "PipelineService"
        ]
      }
    }
  },
  "definitions": {
    "PipelineServiceRunPipelineBody": {
      "type": "object",
      "properties": {
        "input": {
          "type": "object"
        }
      },
      "description": "RunPipelineRequest is the request for triggering a pipeline run."
    },
    "protobufAny": {
      "type": "object",
      "properties": {
        "@type": {
          "type": "string"
        }
      },
      "additionalProperties": {}
    },
    "protobufNullValue": {
      "type": "string",
      "enum": [
        "NULL_VALUE"
      ],
      "default": "NULL_VALUE",
      "description": "`NullValue` is a singleton enumeration to represent the null value for the\n`Value` type union.\n\nThe JSON representation for `NullValue` is JSON `null`.\n\n - NULL_VALUE: Null value."
    },
    "rpcStatus": {
      "type": "object",
      "properties": {
        "code": {
          "type": "integer",
          "format": "int32"
        },
        "message": {
          "type": "string"
        },
        "details": {
          "type": "array",
          "items": {
            "type": "object",
            "$ref": "#/definitions/protobufAny"
          }
        }
      }
    },
    "sirosimesmikurav1CreatePipelineRequest": {
      "type": "object",
      "properties": {
        "name": {
          "type": "string"
        },
        "description": {
          "type": "string"
        },
        "steps": {
          "type": "object"
        },
        "schedule": {
          "type": "string"
        },
        "isActive": {
          "type": "boolean"
        }
      },
      "description": "CreatePipelineRequest is the request for creating a pipeline definition."
    },
    "sirosimesmikurav1CreatePipelineResponse": {
      "type": "object",
      "properties": {
        "pipeline": {
          "$ref": "#/definitions/v1PipelineDefinition"
        }
      },
      "description": "CreatePipelineResponse is the response after creating a pipeline."
    },
    "sirosimesmikurav1ListPipelinesResponse": {
      "type": "object",
      "properties": {
        "pipelines": {
          "type": "array",
          "items": {
            "type": "object",
            "$ref": "#/definitions/v1PipelineDefinition"
          }
        },
        "pagination": {
          "$ref": "#/definitions/v1PaginationResponse"
        }
      },
      "description": "ListPipelinesResponse is the response for listing pipeline definitions."
    },
    "v1GetPipelineStatusResponse": {
      "type": "object",
      "properties": {
        "run": {
          "$ref": "#/definitions/v1PipelineRun"
        },
        "steps": {
          "type": "array",
          "items": {
            "type": "object",
            "$ref": "#/definitions/v1PipelineStep"
          }
        }
      },
      "description": "GetPipelineStatusResponse is the response containing a pipeline run with steps."
    },
    "v1PaginationRequest": {
      "type": "object",
      "properties": {
        "page": {
          "type": "integer",
          "format": "int32",
          "description": "Page number (1-indexed)."
        },
        "pageSize": {
          "type": "integer",
          "format": "int32",
          "description": "Number of items per page (max enforced per-service)."
        },
        "sortBy": {
          "type": "string",
          "description": "Field name to sort by."
        },
        "sortOrder": {
          "$ref": "#/definitions/v1SortOrder",
          "description": "Sort direction."
        }
      },
      "description": "PaginationRequest is the standard offset-based pagination input."
    },
    "v1PaginationResponse": {
      "type": "object",
      "properties": {
        "page": {
          "type": "integer",
          "format": "int32"
        },
        "pageSize": {
          "type": "integer",
          "format": "int32"
        },
        "totalItems": {
          "type": "integer",
          "format": "int32",
          "description": "Total number of matching items (may be expensive for large datasets)."
        },
        "totalPages": {
          "type": "integer",
          "format": "int32"
        },
        "hasNext": {
          "type": "boolean"
        },
        "hasPrev": {
          "type": "boolean"
        }
      },
      "description": "PaginationResponse is the standard offset-based pagination output."
    },
    "v1PipelineDefinition": {
      "type": "object",
      "properties": {
        "metadata": {
          "$ref": "#/definitions/v1ResourceMetadata"
        },
        "name": {
          "type": "string",
          "description": "Human-readable pipeline name."
        },
        "description": {
          "type": "string",
          "description": "Description of the pipeline purpose."
        },
        "steps": {
          "type": "object",
          "description": "Flexible JSON definition of pipeline steps."
        },
        "schedule": {
          "type": "string",
          "description": "Cron-like schedule expression (empty for manual-only)."
        },
        "isActive": {
          "type": "boolean",
          "description": "Whether this pipeline is actively scheduled."
        },
        "createdBy": {
          "type": "string",
          "description": "Actor ID who created this pipeline."
        }
      },
      "description": "PipelineDefinition defines an ETL/data pipeline."
    },
    "v1PipelineRun": {
      "type": "object",
      "properties": {
        "id": {
          "type": "string",
          "description": "Unique identifier (UUID format)."
        },
        "pipelineId": {
          "type": "string",
          "description": "Pipeline definition this run belongs to."
        },
        "status": {
          "$ref": "#/definitions/v1PipelineRunStatus",
          "description": "Current execution status."
        },
        "input": {
          "type": "object",
          "description": "Input parameters for this run."
        },
        "output": {
          "type": "object",
          "description": "Output data from this run."
        },
        "startedAt": {
          "type": "string",
          "format": "date-time",
          "description": "When the run started."
        },
        "finishedAt": {
          "type": "string",
          "format": "date-time",
          "description": "When the run finished (null if still running)."
        }
      },
      "description": "PipelineRun represents a single execution of a pipeline."
    },
    "v1PipelineRunStatus": {
      "type": "string",
      "enum": [
        "PIPELINE_RUN_STATUS_UNSPECIFIED",
        "PIPELINE_RUN_STATUS_PENDING",
        "PIPELINE_RUN_STATUS_RUNNING",
        "PIPELINE_RUN_STATUS_COMPLETED",
        "PIPELINE_RUN_STATUS_FAILED"
      ],
      "default": "PIPELINE_RUN_STATUS_UNSPECIFIED",
      "description": "PipelineRunStatus represents the execution state of a pipeline run."
    },
    "v1PipelineStep": {
      "type": "object",
      "properties": {
        "id": {
          "type": "string",
          "description": "Unique identifier (UUID format)."
        },
        "runId": {
          "type": "string",
          "description": "Pipeline run this step belongs to."
        },
        "stepName": {
          "type": "string",
          "description": "Name of the step."
        },
        "status": {
          "$ref": "#/definitions/v1PipelineStepStatus",
          "description": "Current execution status."
        },
        "input": {
          "type": "object",
          "description": "Input data for this step."
        },
        "output": {
          "type": "object",
          "description": "Output data from this step."
        },
        "error": {
          "type": "string",
          "description": "Error message if the step failed."
        },
        "startedAt": {
          "type": "string",
          "format": "date-time"
        },
        "finishedAt": {
          "type": "string",
          "format": "date-time"
        }
      },
      "description": "PipelineStep represents a single step within a pipeline run."
    },
    "v1PipelineStepStatus": {
      "type": "string",
      "enum": [
        "PIPELINE_STEP_STATUS_UNSPECIFIED",
        "PIPELINE_STEP_STATUS_PENDING",
        "PIPELINE_STEP_STATUS_RUNNING",
        "PIPELINE_STEP_STATUS_COMPLETED",
        "PIPELINE_STEP_STATUS_FAILED",
        "PIPELINE_STEP_STATUS_SKIPPED"
      ],
      "default": "PIPELINE_STEP_STATUS_UNSPECIFIED",
      "description": "PipelineStepStatus represents the execution state of a pipeline step."
    },
    "v1ResourceMetadata": {
      "type": "object",
      "properties": {
        "id": {
          "type": "string",
          "description": "Unique identifier (UUID format recommended)."
        },
        "createdAt": {
          "type": "string",
          "format": "date-time",
          "description": "Timestamp when the resource was created."
        },
        "updatedAt": {
          "type": "string",
          "format": "date-time",
          "description": "Timestamp of the last update."
        },
        "deletedAt": {
          "type": "string",
          "format": "date-time",
          "description": "Soft-delete timestamp (null if not deleted).\nFor RESTRICTED resources, see SECURITY.md for physical deletion policy."
        },
        "createdBy": {
          "type": "string",
          "description": "Actor ID who created this resource."
        },
        "updatedBy": {
          "type": "string",
          "description": "Actor ID who last updated this resource."
        },
        "version": {
          "type": "string",
          "format": "int64",
          "description": "Optimistic concurrency version counter."
        },
        "labels": {
          "type": "object",
          "additionalProperties": {
            "type": "string"
          },
          "description": "Arbitrary key-value labels for filtering and organization."
        },
        "annotations": {
          "type": "object",
          "additionalProperties": {
            "type": "string"
          },
          "description": "Arbitrary key-value annotations for tooling metadata."
        },
        "securityLevel": {
          "$ref": "#/definitions/v1SecurityLevel",
          "description": "Security classification level for this resource (CISO directive).\nDefault when unspecified: treated as INTERNAL."
        }
      },
      "description": "ResourceMetadata provides standard metadata for all Sirosimes resources.\nEvery domain entity across all products should embed this message to ensure\nconsistent tracking, versioning, and security classification.\n\nRelated types:\n  - Actor/ActorRef (actor.proto): created_by/updated_by reference Actor IDs.\n  - AuditLog (audit.proto): changes to resources are tracked via audit events.\n  - SecurityLevel: controls access, encryption, and retention policies.\n\nDefault behavior for security_level:\n  When security_level is UNSPECIFIED (0), domain services SHOULD treat the resource\n  as INTERNAL (level 2) by default. This ensures that resources without explicit\n  classification are not accidentally treated as PUBLIC. Services MAY override this\n  default with stricter levels based on their domain requirements."
    },
    "v1RunPipelineResponse": {
      "type": "object",
      "properties": {
        "run": {
          "$ref": "#/definitions/v1PipelineRun"
        }
      },
      "description": "RunPipelineResponse is the response after triggering a pipeline run."
    },
    "v1SecurityLevel": {
      "type": "string",
      "enum": [
        "SECURITY_LEVEL_UNSPECIFIED",
        "SECURITY_LEVEL_PUBLIC",
        "SECURITY_LEVEL_INTERNAL",
        "SECURITY_LEVEL_CONFIDENTIAL",
        "SECURITY_LEVEL_RESTRICTED"
      ],
      "default": "SECURITY_LEVEL_UNSPECIFIED",
      "description": "SecurityLevel classifies data sensitivity per CISO directive (ISO 27001 aligned).\n\nClassification guide:\n  PUBLIC (1)       — Marketing content, public documentation, open-source code.\n                     Encryption: transit only. Logging: optional. Retention: unlimited.\n  INTERNAL (2)     — Internal wikis, team communications, non-sensitive business data.\n                     Encryption: transit required. Logging: optional. Retention: 3 years.\n  CONFIDENTIAL (3) — Financial reports, HR records, customer data, business strategies.\n                     Encryption: transit + at-rest. Logging: required. Retention: 1 year.\n                     Masking required when exposed externally.\n  RESTRICTED (4)   — PII, credentials, API keys, authentication tokens, audit trails.\n                     Encryption: transit + at-rest + field-level. Logging: required + tamper detection.\n                     Retention: 6 months. Masking: always required.\n\n - SECURITY_LEVEL_PUBLIC: Open data, no access restrictions. Marketing, public docs.\n - SECURITY_LEVEL_INTERNAL: Internal use only. Team wikis, non-sensitive business data.\n - SECURITY_LEVEL_CONFIDENTIAL: Business-sensitive, need-to-know basis. Financial, HR, customer data.\n - SECURITY_LEVEL_RESTRICTED: Highest sensitivity. PII, credentials, tokens, audit trails."
    },
    "v1SortOrder": {
      "type": "string",
      "enum": [
        "SORT_ORDER_UNSPECIFIED",
        "SORT_ORDER_ASC",
        "SORT_ORDER_DESC"
      ],
      "default": "SORT_ORDER_UNSPECIFIED",
      "description": "SortOrder specifies the sort direction."
    }
  }
}
